bdd_file/__init__.py
bdd_file/client.py
bdd_file/exception.py
bdd_file/invoke_api.py
bdd_file/models.py
bdd_file/settings.py
bdd_file_client-0.7.6.dist-info/METADATA
bdd_file_client-0.7.6.dist-info/WHEEL
bdd_file_client-0.7.6.dist-info/licenses/LICENSE
bdd_file_client-0.7.6.dist-info/RECORD
